{
  "version": 1,
  "page": "market-clock",
  "generatedAt": "2026-07-09T23:44:25.104Z",
  "refreshCadence": "Target 10-15 minutes when a backend scheduler is available; static hosts may refresh less frequently.",
  "methodology": "The frontend reads only this generated JSON. OKX public tickers provide crypto, equity-swap proxy, and CL index proxy prices. CoinMarketCap supplies crypto market caps when CMC_PRO_API_KEY is configured in backend or CI. Session states are calculated locally from market-hour rules: U.S. risk assets include night, pre-market, regular, and after-hours blocks; China uses call auction, continuous trading, closing auction, and after-hours blocks; Korea uses pre-market, regular, and after-hours sessions.",
  "failures": [],
  "markets": [
    {
      "id": "crypto",
      "displayName": "Crypto",
      "displayNameZh": "加密市场",
      "timezone": "UTC",
      "stateModel": "always_open",
      "assets": [
        "BTC",
        "USDT",
        "HYPE",
        "BNB"
      ]
    },
    {
      "id": "us",
      "displayName": "U.S. risk",
      "displayNameZh": "美国风险",
      "timezone": "America/New_York",
      "stateModel": "premarket_regular_afterhours",
      "premarketOpen": "04:00",
      "regularOpen": "09:30",
      "regularClose": "16:00",
      "afterhoursClose": "20:00",
      "nightOpen": "20:00",
      "nightClose": "04:00",
      "assets": [
        "TSLA",
        "NVDA",
        "MSFT",
        "CL"
      ]
    },
    {
      "id": "kr",
      "displayName": "Korea",
      "displayNameZh": "韩国市场",
      "timezone": "Asia/Seoul",
      "stateModel": "premarket_regular_afterhours",
      "premarketOpen": "08:30",
      "regularOpen": "09:00",
      "regularClose": "15:30",
      "afterhoursClose": "18:00",
      "assets": [
        "KOSPI200",
        "SAMSUNG",
        "SKHYNIX"
      ]
    },
    {
      "id": "cn",
      "displayName": "China",
      "displayNameZh": "中国市场",
      "timezone": "Asia/Shanghai",
      "stateModel": "china_auction_regular_afterhours",
      "auctionOpen": "09:15",
      "regularOpen": "09:30",
      "lunchStart": "11:30",
      "lunchEnd": "13:00",
      "closingAuctionOpen": "14:57",
      "regularClose": "15:00",
      "afterhoursClose": "15:30",
      "assets": [
        "CSI500",
        "SSE50"
      ]
    }
  ],
  "assets": [
    {
      "symbol": "BTC",
      "name": "Bitcoin",
      "nameZh": "Bitcoin",
      "market": "crypto",
      "quote": "USDT",
      "localQuote": null,
      "price": 63284.8,
      "changePct": 1.6078120333828942,
      "changeBasis": "UTC day",
      "marketCapUsd": 1267970218344.4924,
      "marketCapStatus": "available",
      "marketCapAsOf": "2026-07-09T23:43:05.000Z",
      "asOf": "2026-07-09T23:44:23.057Z",
      "sourceKind": "official_public",
      "sourceLabel": "OKX spot ticker",
      "marketCapSourceLabel": "CoinMarketCap quotes/latest",
      "quality": null,
      "components": null
    },
    {
      "symbol": "USDT",
      "name": "Tether USDt",
      "nameZh": "Tether USDt",
      "market": "crypto",
      "quote": "USD",
      "localQuote": null,
      "price": 0.9993,
      "changePct": 0.010008006405122997,
      "changeBasis": "UTC day",
      "marketCapUsd": 184144788593.05728,
      "marketCapStatus": "available",
      "marketCapAsOf": "2026-07-09T23:43:05.000Z",
      "asOf": "2026-07-09T23:44:23.060Z",
      "sourceKind": "official_public",
      "sourceLabel": "OKX spot ticker",
      "marketCapSourceLabel": "CoinMarketCap quotes/latest",
      "quality": "USDT/USD is a peg-pressure proxy, not a direct flow measurement.",
      "components": null
    },
    {
      "symbol": "HYPE",
      "name": "Hyperliquid",
      "nameZh": "Hyperliquid",
      "market": "crypto",
      "quote": "USDT",
      "localQuote": null,
      "price": 67.131,
      "changePct": -0.7583821181479586,
      "changeBasis": "UTC day",
      "marketCapUsd": 16973254961.249784,
      "marketCapStatus": "available",
      "marketCapAsOf": "2026-07-09T23:43:05.000Z",
      "asOf": "2026-07-09T23:44:22.969Z",
      "sourceKind": "official_public",
      "sourceLabel": "OKX spot ticker",
      "marketCapSourceLabel": "CoinMarketCap quotes/latest",
      "quality": null,
      "components": null
    },
    {
      "symbol": "BNB",
      "name": "BNB",
      "nameZh": "BNB",
      "market": "crypto",
      "quote": "USDT",
      "localQuote": null,
      "price": 568.9,
      "changePct": 0.017580872011255758,
      "changeBasis": "UTC day",
      "marketCapUsd": 76624989751.04521,
      "marketCapStatus": "available",
      "marketCapAsOf": "2026-07-09T23:43:05.000Z",
      "asOf": "2026-07-09T23:44:23.665Z",
      "sourceKind": "official_public",
      "sourceLabel": "OKX spot ticker",
      "marketCapSourceLabel": "CoinMarketCap quotes/latest",
      "quality": null,
      "components": null
    },
    {
      "symbol": "TSLA",
      "name": "Tesla",
      "nameZh": "Tesla",
      "market": "us",
      "quote": "USD",
      "localQuote": null,
      "price": 405.4,
      "changePct": 2.7812286083715665,
      "changeBasis": "UTC day",
      "marketCapUsd": null,
      "marketCapStatus": "unavailable",
      "marketCapAsOf": null,
      "asOf": "2026-07-09T23:44:23.077Z",
      "sourceKind": "proxy",
      "sourceLabel": "OKX swap ticker proxy",
      "marketCapSourceLabel": null,
      "quality": "OKX equity swap proxy; official U.S. equity feed pending.",
      "components": null
    },
    {
      "symbol": "NVDA",
      "name": "NVIDIA",
      "nameZh": "NVIDIA",
      "market": "us",
      "quote": "USD",
      "localQuote": null,
      "price": 202.61,
      "changePct": -0.6034144427001519,
      "changeBasis": "UTC day",
      "marketCapUsd": null,
      "marketCapStatus": "unavailable",
      "marketCapAsOf": null,
      "asOf": "2026-07-09T23:44:23.565Z",
      "sourceKind": "proxy",
      "sourceLabel": "OKX swap ticker proxy",
      "marketCapSourceLabel": null,
      "quality": "OKX equity swap proxy; official U.S. equity feed pending.",
      "components": null
    },
    {
      "symbol": "MSFT",
      "name": "Microsoft",
      "nameZh": "Microsoft",
      "market": "us",
      "quote": "USD",
      "localQuote": null,
      "price": 384.87,
      "changePct": 0.13008299294950176,
      "changeBasis": "UTC day",
      "marketCapUsd": null,
      "marketCapStatus": "unavailable",
      "marketCapAsOf": null,
      "asOf": "2026-07-09T23:44:24.161Z",
      "sourceKind": "proxy",
      "sourceLabel": "OKX swap ticker proxy",
      "marketCapSourceLabel": null,
      "quality": "OKX equity swap proxy; official U.S. equity feed pending.",
      "components": null
    },
    {
      "symbol": "CL",
      "name": "OKX CL Index",
      "nameZh": "OKX CL 指数",
      "market": "us",
      "quote": "USD",
      "localQuote": null,
      "price": 71.834,
      "changePct": -3.463197645509398,
      "changeBasis": "UTC day",
      "marketCapUsd": null,
      "marketCapStatus": "not_applicable",
      "marketCapAsOf": null,
      "asOf": "2026-07-09T23:44:24.372Z",
      "sourceKind": "proxy",
      "sourceLabel": "OKX index ticker",
      "marketCapSourceLabel": null,
      "quality": "OKX CL index proxy; primarily Hyperliquid Oracle plus OKX linear perpetual components.",
      "components": [
        {
          "exchange": "Binance_Index",
          "symbol": "CL/USDT",
          "weight": 0.5
        },
        {
          "exchange": "OKX_LINEAR_PERPETUAL",
          "symbol": "CL/USDT",
          "weight": 0.5
        }
      ]
    },
    {
      "symbol": "KOSPI200",
      "name": "KOSPI 200",
      "nameZh": "KOSPI 200",
      "market": "kr",
      "quote": "USD",
      "localQuote": null,
      "price": null,
      "changePct": null,
      "changeBasis": null,
      "marketCapUsd": null,
      "marketCapStatus": "unavailable",
      "marketCapAsOf": null,
      "asOf": null,
      "sourceKind": "pending",
      "sourceLabel": "Price source pending; status rotation is calculated locally from KRX pre-market, regular, and after-hours session rules.",
      "marketCapSourceLabel": null,
      "quality": "Price source pending; status rotation is calculated locally from KRX pre-market, regular, and after-hours session rules.",
      "components": null
    },
    {
      "symbol": "SAMSUNG",
      "name": "Samsung Electronics",
      "nameZh": "Samsung Electronics",
      "market": "kr",
      "quote": "USD",
      "localQuote": "KRW",
      "price": null,
      "changePct": null,
      "changeBasis": null,
      "marketCapUsd": null,
      "marketCapStatus": "unavailable",
      "marketCapAsOf": null,
      "asOf": null,
      "sourceKind": "pending",
      "sourceLabel": "KRW price and USD conversion source pending.",
      "marketCapSourceLabel": null,
      "quality": "KRW price and USD conversion source pending.",
      "components": null
    },
    {
      "symbol": "SKHYNIX",
      "name": "SK hynix",
      "nameZh": "SK hynix",
      "market": "kr",
      "quote": "USD",
      "localQuote": "KRW",
      "price": null,
      "changePct": null,
      "changeBasis": null,
      "marketCapUsd": null,
      "marketCapStatus": "unavailable",
      "marketCapAsOf": null,
      "asOf": null,
      "sourceKind": "pending",
      "sourceLabel": "KRW price and USD conversion source pending.",
      "marketCapSourceLabel": null,
      "quality": "KRW price and USD conversion source pending.",
      "components": null
    },
    {
      "symbol": "CSI500",
      "name": "CSI 500",
      "nameZh": "中证500",
      "market": "cn",
      "quote": "CNY",
      "localQuote": null,
      "price": null,
      "changePct": null,
      "changeBasis": null,
      "marketCapUsd": null,
      "marketCapStatus": "unavailable",
      "marketCapAsOf": null,
      "asOf": null,
      "sourceKind": "pending",
      "sourceLabel": "China index price source pending; market cap may remain unavailable.",
      "marketCapSourceLabel": null,
      "quality": "China index price source pending; market cap may remain unavailable.",
      "components": null
    },
    {
      "symbol": "SSE50",
      "name": "SSE 50",
      "nameZh": "上证50",
      "market": "cn",
      "quote": "CNY",
      "localQuote": null,
      "price": null,
      "changePct": null,
      "changeBasis": null,
      "marketCapUsd": null,
      "marketCapStatus": "unavailable",
      "marketCapAsOf": null,
      "asOf": null,
      "sourceKind": "pending",
      "sourceLabel": "China index price source pending; market cap may remain unavailable.",
      "marketCapSourceLabel": null,
      "quality": "China index price source pending; market cap may remain unavailable.",
      "components": null
    }
  ],
  "sources": {
    "okx": "https://www.okx.com/docs-v5/en/",
    "cmc": "https://coinmarketcap.com/api/documentation/v1/",
    "note": "No provider credentials are emitted to the frontend cache."
  }
}
